{"match_id": "4970fd9b-45c8-485a-a233-20996eccd351", "map_id": "AmbroseValley", "day": "February_13", "events": [{"user_id": "98de5ab3-bf0e-4f9b-ad03-43b8950ae486", "x": 267.02, "z": -44.97, "ts": "1970-01-21 11:56:29.534000", "event": "Position", "is_bot": false}, {"user_id": "98de5ab3-bf0e-4f9b-ad03-43b8950ae486", "x": 257.8, "z": -49.83, "ts": "1970-01-21 11:56:29.550000", "event": "Position", "is_bot": false}, {"user_id": "98de5ab3-bf0e-4f9b-ad03-43b8950ae486", "x": 248.58, "z": -58.18, "ts": "1970-01-21 11:56:29.555000", "event": "Position", "is_bot": false}, {"user_id": "98de5ab3-bf0e-4f9b-ad03-43b8950ae486", "x": 236.72, "z": -39.37, "ts": "1970-01-21 11:56:29.560000", "event": "Position", "is_bot": false}, {"user_id": "98de5ab3-bf0e-4f9b-ad03-43b8950ae486", "x": 226.56, "z": -22.19, "ts": "1970-01-21 11:56:29.565000", "event": "Position", "is_bot": false}, {"user_id": "98de5ab3-bf0e-4f9b-ad03-43b8950ae486", "x": 203.33, "z": -4.96, "ts": "1970-01-21 11:56:29.570000", "event": "Position", "is_bot": false}, {"user_id": "98de5ab3-bf0e-4f9b-ad03-43b8950ae486", "x": 175.48, "z": 11.05, "ts": "1970-01-21 11:56:29.575000", "event": "Position", "is_bot": false}, {"user_id": "98de5ab3-bf0e-4f9b-ad03-43b8950ae486", "x": 158.59, "z": 35.31, "ts": "1970-01-21 11:56:29.580000", "event": "Position", "is_bot": false}, {"user_id": "98de5ab3-bf0e-4f9b-ad03-43b8950ae486", "x": 143.03, "z": 52.34, "ts": "1970-01-21 11:56:29.585000", "event": "Position", "is_bot": false}, {"user_id": "98de5ab3-bf0e-4f9b-ad03-43b8950ae486", "x": 138.95, "z": 60.13, "ts": "1970-01-21 11:56:29.590000", "event": "Position", "is_bot": false}, {"user_id": "98de5ab3-bf0e-4f9b-ad03-43b8950ae486", "x": 144.75, "z": 74.32, "ts": "1970-01-21 11:56:29.595000", "event": "Position", "is_bot": false}, {"user_id": "98de5ab3-bf0e-4f9b-ad03-43b8950ae486", "x": 149.64, "z": 75.11, "ts": "1970-01-21 11:56:29.597000", "event": "Loot", "is_bot": false}, {"user_id": "98de5ab3-bf0e-4f9b-ad03-43b8950ae486", "x": 149.56, "z": 77.46, "ts": "1970-01-21 11:56:29.600000", "event": "Position", "is_bot": false}, {"user_id": "98de5ab3-bf0e-4f9b-ad03-43b8950ae486", "x": 156.46, "z": 83.64, "ts": "1970-01-21 11:56:29.605000", "event": "Position", "is_bot": false}, {"user_id": "98de5ab3-bf0e-4f9b-ad03-43b8950ae486", "x": 164.17, "z": 84.04, "ts": "1970-01-21 11:56:29.610000", "event": "Position", "is_bot": false}, {"user_id": "98de5ab3-bf0e-4f9b-ad03-43b8950ae486", "x": 168.34, "z": 83.67, "ts": "1970-01-21 11:56:29.614000", "event": "Loot", "is_bot": false}, {"user_id": "98de5ab3-bf0e-4f9b-ad03-43b8950ae486", "x": 168.02, "z": 83.56, "ts": "1970-01-21 11:56:29.615000", "event": "Position", "is_bot": false}, {"user_id": "98de5ab3-bf0e-4f9b-ad03-43b8950ae486", "x": 162.58, "z": 87.41, "ts": "1970-01-21 11:56:29.620000", "event": "Position", "is_bot": false}, {"user_id": "98de5ab3-bf0e-4f9b-ad03-43b8950ae486", "x": 171.83, "z": 86.84, "ts": "1970-01-21 11:56:29.625000", "event": "Position", "is_bot": false}, {"user_id": "98de5ab3-bf0e-4f9b-ad03-43b8950ae486", "x": 175.4, "z": 86.61, "ts": "1970-01-21 11:56:29.630000", "event": "Position", "is_bot": false}, {"user_id": "98de5ab3-bf0e-4f9b-ad03-43b8950ae486", "x": 180.74, "z": 86.65, "ts": "1970-01-21 11:56:29.635000", "event": "Position", "is_bot": false}, {"user_id": "98de5ab3-bf0e-4f9b-ad03-43b8950ae486", "x": 186.5, "z": 84.35, "ts": "1970-01-21 11:56:29.640000", "event": "Position", "is_bot": false}, {"user_id": "98de5ab3-bf0e-4f9b-ad03-43b8950ae486", "x": 181.27, "z": 79.97, "ts": "1970-01-21 11:56:29.645000", "event": "Position", "is_bot": false}, {"user_id": "98de5ab3-bf0e-4f9b-ad03-43b8950ae486", "x": 179.25, "z": 75.46, "ts": "1970-01-21 11:56:29.648000", "event": "Loot", "is_bot": false}, {"user_id": "98de5ab3-bf0e-4f9b-ad03-43b8950ae486", "x": 180.93, "z": 74.42, "ts": "1970-01-21 11:56:29.650000", "event": "Position", "is_bot": false}, {"user_id": "98de5ab3-bf0e-4f9b-ad03-43b8950ae486", "x": 173.41, "z": 80.7, "ts": "1970-01-21 11:56:29.660000", "event": "Position", "is_bot": false}, {"user_id": "98de5ab3-bf0e-4f9b-ad03-43b8950ae486", "x": 177.63, "z": 83.89, "ts": "1970-01-21 11:56:29.665000", "event": "Position", "is_bot": false}, {"user_id": "98de5ab3-bf0e-4f9b-ad03-43b8950ae486", "x": 177.62, "z": 83.84, "ts": "1970-01-21 11:56:29.667000", "event": "Loot", "is_bot": false}, {"user_id": "98de5ab3-bf0e-4f9b-ad03-43b8950ae486", "x": 175.14, "z": 76.48, "ts": "1970-01-21 11:56:29.670000", "event": "Position", "is_bot": false}, {"user_id": "98de5ab3-bf0e-4f9b-ad03-43b8950ae486", "x": 174.18, "z": 72.1, "ts": "1970-01-21 11:56:29.672000", "event": "Loot", "is_bot": false}, {"user_id": "98de5ab3-bf0e-4f9b-ad03-43b8950ae486", "x": 175.08, "z": 69.61, "ts": "1970-01-21 11:56:29.675000", "event": "Position", "is_bot": false}, {"user_id": "98de5ab3-bf0e-4f9b-ad03-43b8950ae486", "x": 173.0, "z": 72.34, "ts": "1970-01-21 11:56:29.680000", "event": "Position", "is_bot": false}, {"user_id": "98de5ab3-bf0e-4f9b-ad03-43b8950ae486", "x": 171.7, "z": 76.83, "ts": "1970-01-21 11:56:29.685000", "event": "Position", "is_bot": false}, {"user_id": "98de5ab3-bf0e-4f9b-ad03-43b8950ae486", "x": 171.44, "z": 81.26, "ts": "1970-01-21 11:56:29.690000", "event": "Position", "is_bot": false}, {"user_id": "98de5ab3-bf0e-4f9b-ad03-43b8950ae486", "x": 181.59, "z": 91.24, "ts": "1970-01-21 11:56:29.705000", "event": "Position", "is_bot": false}, {"user_id": "98de5ab3-bf0e-4f9b-ad03-43b8950ae486", "x": 186.68, "z": 106.01, "ts": "1970-01-21 11:56:29.710000", "event": "Position", "is_bot": false}, {"user_id": "98de5ab3-bf0e-4f9b-ad03-43b8950ae486", "x": 206.45, "z": 122.83, "ts": "1970-01-21 11:56:29.715000", "event": "Position", "is_bot": false}, {"user_id": "98de5ab3-bf0e-4f9b-ad03-43b8950ae486", "x": 219.01, "z": 139.13, "ts": "1970-01-21 11:56:29.721000", "event": "Position", "is_bot": false}, {"user_id": "98de5ab3-bf0e-4f9b-ad03-43b8950ae486", "x": 206.58, "z": 166.1, "ts": "1970-01-21 11:56:29.726000", "event": "Position", "is_bot": false}, {"user_id": "98de5ab3-bf0e-4f9b-ad03-43b8950ae486", "x": 193.69, "z": 196.1, "ts": "1970-01-21 11:56:29.731000", "event": "Position", "is_bot": false}, {"user_id": "98de5ab3-bf0e-4f9b-ad03-43b8950ae486", "x": 193.79, "z": 202.61, "ts": "1970-01-21 11:56:29.733000", "event": "Loot", "is_bot": false}, {"user_id": "98de5ab3-bf0e-4f9b-ad03-43b8950ae486", "x": 193.79, "z": 202.61, "ts": "1970-01-21 11:56:29.736000", "event": "Position", "is_bot": false}, {"user_id": "98de5ab3-bf0e-4f9b-ad03-43b8950ae486", "x": 185.9, "z": 195.49, "ts": "1970-01-21 11:56:29.741000", "event": "Position", "is_bot": false}, {"user_id": "98de5ab3-bf0e-4f9b-ad03-43b8950ae486", "x": 192.18, "z": 167.38, "ts": "1970-01-21 11:56:29.746000", "event": "Position", "is_bot": false}, {"user_id": "98de5ab3-bf0e-4f9b-ad03-43b8950ae486", "x": 178.06, "z": 138.67, "ts": "1970-01-21 11:56:29.751000", "event": "Position", "is_bot": false}, {"user_id": "98de5ab3-bf0e-4f9b-ad03-43b8950ae486", "x": 170.63, "z": 120.39, "ts": "1970-01-21 11:56:29.756000", "event": "Position", "is_bot": false}, {"user_id": "98de5ab3-bf0e-4f9b-ad03-43b8950ae486", "x": 162.77, "z": 92.1, "ts": "1970-01-21 11:56:29.761000", "event": "Position", "is_bot": false}, {"user_id": "98de5ab3-bf0e-4f9b-ad03-43b8950ae486", "x": 160.57, "z": 73.37, "ts": "1970-01-21 11:56:29.766000", "event": "Position", "is_bot": false}, {"user_id": "98de5ab3-bf0e-4f9b-ad03-43b8950ae486", "x": 151.94, "z": 57.03, "ts": "1970-01-21 11:56:29.770000", "event": "BotKill", "is_bot": false}, {"user_id": "98de5ab3-bf0e-4f9b-ad03-43b8950ae486", "x": 151.94, "z": 57.03, "ts": "1970-01-21 11:56:29.771000", "event": "Position", "is_bot": false}, {"user_id": "98de5ab3-bf0e-4f9b-ad03-43b8950ae486", "x": 147.4, "z": 57.92, "ts": "1970-01-21 11:56:29.774000", "event": "Loot", "is_bot": false}, {"user_id": "98de5ab3-bf0e-4f9b-ad03-43b8950ae486", "x": 147.4, "z": 57.92, "ts": "1970-01-21 11:56:29.775000", "event": "Loot", "is_bot": false}, {"user_id": "98de5ab3-bf0e-4f9b-ad03-43b8950ae486", "x": 147.01, "z": 56.95, "ts": "1970-01-21 11:56:29.776000", "event": "Position", "is_bot": false}, {"user_id": "98de5ab3-bf0e-4f9b-ad03-43b8950ae486", "x": 167.56, "z": 60.35, "ts": "1970-01-21 11:56:29.781000", "event": "Position", "is_bot": false}, {"user_id": "98de5ab3-bf0e-4f9b-ad03-43b8950ae486", "x": 167.69, "z": 60.2, "ts": "1970-01-21 11:56:29.781000", "event": "Loot", "is_bot": false}, {"user_id": "98de5ab3-bf0e-4f9b-ad03-43b8950ae486", "x": 172.67, "z": 62.02, "ts": "1970-01-21 11:56:29.786000", "event": "Position", "is_bot": false}, {"user_id": "98de5ab3-bf0e-4f9b-ad03-43b8950ae486", "x": 180.91, "z": 72.41, "ts": "1970-01-21 11:56:29.791000", "event": "Position", "is_bot": false}, {"user_id": "98de5ab3-bf0e-4f9b-ad03-43b8950ae486", "x": 164.88, "z": 75.7, "ts": "1970-01-21 11:56:29.796000", "event": "Position", "is_bot": false}, {"user_id": "98de5ab3-bf0e-4f9b-ad03-43b8950ae486", "x": 147.21, "z": 59.53, "ts": "1970-01-21 11:56:29.801000", "event": "Position", "is_bot": false}, {"user_id": "98de5ab3-bf0e-4f9b-ad03-43b8950ae486", "x": 129.97, "z": 34.6, "ts": "1970-01-21 11:56:29.806000", "event": "Position", "is_bot": false}, {"user_id": "98de5ab3-bf0e-4f9b-ad03-43b8950ae486", "x": 123.3, "z": 16.43, "ts": "1970-01-21 11:56:29.811000", "event": "Position", "is_bot": false}, {"user_id": "98de5ab3-bf0e-4f9b-ad03-43b8950ae486", "x": 106.16, "z": 1.22, "ts": "1970-01-21 11:56:29.816000", "event": "Position", "is_bot": false}, {"user_id": "98de5ab3-bf0e-4f9b-ad03-43b8950ae486", "x": 97.52, "z": -6.55, "ts": "1970-01-21 11:56:29.821000", "event": "Position", "is_bot": false}, {"user_id": "98de5ab3-bf0e-4f9b-ad03-43b8950ae486", "x": 112.01, "z": -34.48, "ts": "1970-01-21 11:56:29.826000", "event": "Position", "is_bot": false}, {"user_id": "98de5ab3-bf0e-4f9b-ad03-43b8950ae486", "x": 110.0, "z": -47.27, "ts": "1970-01-21 11:56:29.831000", "event": "Position", "is_bot": false}, {"user_id": "98de5ab3-bf0e-4f9b-ad03-43b8950ae486", "x": 110.87, "z": -45.13, "ts": "1970-01-21 11:56:29.839000", "event": "BotKilled", "is_bot": false}, {"user_id": "98de5ab3-bf0e-4f9b-ad03-43b8950ae486", "x": 110.92, "z": -45.12, "ts": "1970-01-21 11:56:29.841000", "event": "Position", "is_bot": false}]}