{"match_id": "7a8c086d-b5f2-4dc5-9c76-3f390a9d3f0d", "map_id": "AmbroseValley", "day": "February_12", "events": [{"user_id": "86b019b9-dd32-4fe0-baf4-174a1f51fa68", "x": -301.55, "z": -349.89, "ts": "1970-01-21 11:54:53.981000", "event": "Position", "is_bot": false}, {"user_id": "86b019b9-dd32-4fe0-baf4-174a1f51fa68", "x": -291.25, "z": -352.28, "ts": "1970-01-21 11:54:54.027000", "event": "Position", "is_bot": false}, {"user_id": "86b019b9-dd32-4fe0-baf4-174a1f51fa68", "x": -263.93, "z": -355.82, "ts": "1970-01-21 11:54:54.032000", "event": "Position", "is_bot": false}, {"user_id": "86b019b9-dd32-4fe0-baf4-174a1f51fa68", "x": -240.75, "z": -353.3, "ts": "1970-01-21 11:54:54.037000", "event": "Position", "is_bot": false}, {"user_id": "86b019b9-dd32-4fe0-baf4-174a1f51fa68", "x": -236.4, "z": -351.14, "ts": "1970-01-21 11:54:54.042000", "event": "Position", "is_bot": false}, {"user_id": "86b019b9-dd32-4fe0-baf4-174a1f51fa68", "x": -226.88, "z": -347.04, "ts": "1970-01-21 11:54:54.047000", "event": "Position", "is_bot": false}, {"user_id": "86b019b9-dd32-4fe0-baf4-174a1f51fa68", "x": -227.76, "z": -328.97, "ts": "1970-01-21 11:54:54.052000", "event": "Position", "is_bot": false}, {"user_id": "86b019b9-dd32-4fe0-baf4-174a1f51fa68", "x": -227.38, "z": -329.02, "ts": "1970-01-21 11:54:54.053000", "event": "Loot", "is_bot": false}, {"user_id": "86b019b9-dd32-4fe0-baf4-174a1f51fa68", "x": -227.04, "z": -318.26, "ts": "1970-01-21 11:54:54.057000", "event": "Position", "is_bot": false}, {"user_id": "86b019b9-dd32-4fe0-baf4-174a1f51fa68", "x": -212.01, "z": -311.91, "ts": "1970-01-21 11:54:54.062000", "event": "Position", "is_bot": false}, {"user_id": "86b019b9-dd32-4fe0-baf4-174a1f51fa68", "x": -212.01, "z": -311.91, "ts": "1970-01-21 11:54:54.090000", "event": "BotKilled", "is_bot": false}]}