{"match_id": "9b2e9d02-8116-4ab0-ae78-959d33da56d4", "map_id": "Lockdown", "day": "February_12", "events": [{"user_id": "f334c236-f0f6-4fa3-9116-3a22e14a2151", "x": -176.71, "z": -254.08, "ts": "1970-01-21 11:54:50.901000", "event": "Position", "is_bot": false}, {"user_id": "f334c236-f0f6-4fa3-9116-3a22e14a2151", "x": -162.21, "z": -255.56, "ts": "1970-01-21 11:54:50.916000", "event": "Position", "is_bot": false}, {"user_id": "f334c236-f0f6-4fa3-9116-3a22e14a2151", "x": -151.44, "z": -256.64, "ts": "1970-01-21 11:54:50.921000", "event": "Position", "is_bot": false}, {"user_id": "f334c236-f0f6-4fa3-9116-3a22e14a2151", "x": -165.57, "z": -243.5, "ts": "1970-01-21 11:54:50.931000", "event": "Position", "is_bot": false}, {"user_id": "f334c236-f0f6-4fa3-9116-3a22e14a2151", "x": -183.42, "z": -220.99, "ts": "1970-01-21 11:54:50.936000", "event": "Position", "is_bot": false}, {"user_id": "f334c236-f0f6-4fa3-9116-3a22e14a2151", "x": -198.16, "z": -196.82, "ts": "1970-01-21 11:54:50.941000", "event": "Position", "is_bot": false}, {"user_id": "f334c236-f0f6-4fa3-9116-3a22e14a2151", "x": -190.46, "z": -185.39, "ts": "1970-01-21 11:54:50.946000", "event": "Position", "is_bot": false}, {"user_id": "f334c236-f0f6-4fa3-9116-3a22e14a2151", "x": -189.23, "z": -171.54, "ts": "1970-01-21 11:54:50.951000", "event": "Position", "is_bot": false}, {"user_id": "f334c236-f0f6-4fa3-9116-3a22e14a2151", "x": -177.11, "z": -164.26, "ts": "1970-01-21 11:54:50.956000", "event": "Position", "is_bot": false}, {"user_id": "f334c236-f0f6-4fa3-9116-3a22e14a2151", "x": -170.91, "z": -179.33, "ts": "1970-01-21 11:54:50.961000", "event": "Position", "is_bot": false}, {"user_id": "f334c236-f0f6-4fa3-9116-3a22e14a2151", "x": -169.41, "z": -185.42, "ts": "1970-01-21 11:54:50.966000", "event": "Position", "is_bot": false}, {"user_id": "f334c236-f0f6-4fa3-9116-3a22e14a2151", "x": -172.35, "z": -194.87, "ts": "1970-01-21 11:54:50.970000", "event": "Loot", "is_bot": false}, {"user_id": "f334c236-f0f6-4fa3-9116-3a22e14a2151", "x": -174.49, "z": -193.92, "ts": "1970-01-21 11:54:50.971000", "event": "Position", "is_bot": false}, {"user_id": "f334c236-f0f6-4fa3-9116-3a22e14a2151", "x": -176.15, "z": -177.05, "ts": "1970-01-21 11:54:50.976000", "event": "Position", "is_bot": false}, {"user_id": "f334c236-f0f6-4fa3-9116-3a22e14a2151", "x": -179.36, "z": -154.09, "ts": "1970-01-21 11:54:50.981000", "event": "Position", "is_bot": false}, {"user_id": "f334c236-f0f6-4fa3-9116-3a22e14a2151", "x": -180.64, "z": -141.78, "ts": "1970-01-21 11:54:50.985000", "event": "Loot", "is_bot": false}, {"user_id": "f334c236-f0f6-4fa3-9116-3a22e14a2151", "x": -181.17, "z": -141.9, "ts": "1970-01-21 11:54:50.986000", "event": "Position", "is_bot": false}, {"user_id": "f334c236-f0f6-4fa3-9116-3a22e14a2151", "x": -185.81, "z": -129.73, "ts": "1970-01-21 11:54:50.991000", "event": "Position", "is_bot": false}, {"user_id": "f334c236-f0f6-4fa3-9116-3a22e14a2151", "x": -183.37, "z": -125.23, "ts": "1970-01-21 11:54:50.996000", "event": "Position", "is_bot": false}, {"user_id": "f334c236-f0f6-4fa3-9116-3a22e14a2151", "x": -177.32, "z": -126.45, "ts": "1970-01-21 11:54:51.001000", "event": "Position", "is_bot": false}, {"user_id": "f334c236-f0f6-4fa3-9116-3a22e14a2151", "x": -172.89, "z": -130.49, "ts": "1970-01-21 11:54:51.006000", "event": "Position", "is_bot": false}, {"user_id": "f334c236-f0f6-4fa3-9116-3a22e14a2151", "x": -171.07, "z": -129.39, "ts": "1970-01-21 11:54:51.052000", "event": "Position", "is_bot": false}, {"user_id": "f334c236-f0f6-4fa3-9116-3a22e14a2151", "x": -172.98, "z": -122.65, "ts": "1970-01-21 11:54:51.057000", "event": "Position", "is_bot": false}, {"user_id": "f334c236-f0f6-4fa3-9116-3a22e14a2151", "x": -170.19, "z": -114.76, "ts": "1970-01-21 11:54:51.062000", "event": "Position", "is_bot": false}, {"user_id": "f334c236-f0f6-4fa3-9116-3a22e14a2151", "x": -172.5, "z": -115.54, "ts": "1970-01-21 11:54:51.067000", "event": "Position", "is_bot": false}, {"user_id": "f334c236-f0f6-4fa3-9116-3a22e14a2151", "x": -173.34, "z": -103.25, "ts": "1970-01-21 11:54:51.072000", "event": "Position", "is_bot": false}, {"user_id": "f334c236-f0f6-4fa3-9116-3a22e14a2151", "x": -172.59, "z": -80.72, "ts": "1970-01-21 11:54:51.077000", "event": "Position", "is_bot": false}, {"user_id": "f334c236-f0f6-4fa3-9116-3a22e14a2151", "x": -160.06, "z": -81.27, "ts": "1970-01-21 11:54:51.082000", "event": "Position", "is_bot": false}, {"user_id": "f334c236-f0f6-4fa3-9116-3a22e14a2151", "x": -159.35, "z": -81.79, "ts": "1970-01-21 11:54:51.085000", "event": "BotKill", "is_bot": false}, {"user_id": "f334c236-f0f6-4fa3-9116-3a22e14a2151", "x": -157.52, "z": -79.84, "ts": "1970-01-21 11:54:51.087000", "event": "Position", "is_bot": false}, {"user_id": "f334c236-f0f6-4fa3-9116-3a22e14a2151", "x": -149.47, "z": -58.44, "ts": "1970-01-21 11:54:51.092000", "event": "Position", "is_bot": false}, {"user_id": "f334c236-f0f6-4fa3-9116-3a22e14a2151", "x": -149.47, "z": -58.44, "ts": "1970-01-21 11:54:51.093000", "event": "Loot", "is_bot": false}, {"user_id": "f334c236-f0f6-4fa3-9116-3a22e14a2151", "x": -149.47, "z": -58.44, "ts": "1970-01-21 11:54:51.093000", "event": "Loot", "is_bot": false}, {"user_id": "f334c236-f0f6-4fa3-9116-3a22e14a2151", "x": -143.82, "z": -71.25, "ts": "1970-01-21 11:54:51.097000", "event": "Position", "is_bot": false}, {"user_id": "f334c236-f0f6-4fa3-9116-3a22e14a2151", "x": -122.09, "z": -83.46, "ts": "1970-01-21 11:54:51.102000", "event": "Position", "is_bot": false}, {"user_id": "f334c236-f0f6-4fa3-9116-3a22e14a2151", "x": -122.09, "z": -83.46, "ts": "1970-01-21 11:54:51.104000", "event": "Loot", "is_bot": false}, {"user_id": "f334c236-f0f6-4fa3-9116-3a22e14a2151", "x": -122.66, "z": -88.5, "ts": "1970-01-21 11:54:51.107000", "event": "Position", "is_bot": false}, {"user_id": "f334c236-f0f6-4fa3-9116-3a22e14a2151", "x": -122.66, "z": -88.5, "ts": "1970-01-21 11:54:51.107000", "event": "Loot", "is_bot": false}, {"user_id": "f334c236-f0f6-4fa3-9116-3a22e14a2151", "x": -140.97, "z": -99.37, "ts": "1970-01-21 11:54:51.112000", "event": "Position", "is_bot": false}, {"user_id": "f334c236-f0f6-4fa3-9116-3a22e14a2151", "x": -150.29, "z": -102.33, "ts": "1970-01-21 11:54:51.117000", "event": "Position", "is_bot": false}, {"user_id": "f334c236-f0f6-4fa3-9116-3a22e14a2151", "x": -152.26, "z": -116.6, "ts": "1970-01-21 11:54:51.122000", "event": "Position", "is_bot": false}, {"user_id": "f334c236-f0f6-4fa3-9116-3a22e14a2151", "x": -168.18, "z": -101.23, "ts": "1970-01-21 11:54:51.127000", "event": "Position", "is_bot": false}, {"user_id": "f334c236-f0f6-4fa3-9116-3a22e14a2151", "x": -187.02, "z": -79.58, "ts": "1970-01-21 11:54:51.132000", "event": "Position", "is_bot": false}, {"user_id": "f334c236-f0f6-4fa3-9116-3a22e14a2151", "x": -191.88, "z": -66.12, "ts": "1970-01-21 11:54:51.137000", "event": "Position", "is_bot": false}, {"user_id": "f334c236-f0f6-4fa3-9116-3a22e14a2151", "x": -187.1, "z": -67.21, "ts": "1970-01-21 11:54:51.142000", "event": "Position", "is_bot": false}, {"user_id": "f334c236-f0f6-4fa3-9116-3a22e14a2151", "x": -174.75, "z": -60.83, "ts": "1970-01-21 11:54:51.147000", "event": "Position", "is_bot": false}, {"user_id": "f334c236-f0f6-4fa3-9116-3a22e14a2151", "x": -173.09, "z": -58.68, "ts": "1970-01-21 11:54:51.151000", "event": "Loot", "is_bot": false}, {"user_id": "f334c236-f0f6-4fa3-9116-3a22e14a2151", "x": -174.14, "z": -58.86, "ts": "1970-01-21 11:54:51.152000", "event": "Position", "is_bot": false}, {"user_id": "f334c236-f0f6-4fa3-9116-3a22e14a2151", "x": -178.38, "z": -70.17, "ts": "1970-01-21 11:54:51.157000", "event": "Position", "is_bot": false}, {"user_id": "f334c236-f0f6-4fa3-9116-3a22e14a2151", "x": -177.83, "z": -72.67, "ts": "1970-01-21 11:54:51.159000", "event": "Loot", "is_bot": false}, {"user_id": "f334c236-f0f6-4fa3-9116-3a22e14a2151", "x": -183.43, "z": -62.03, "ts": "1970-01-21 11:54:51.167000", "event": "Position", "is_bot": false}, {"user_id": "f334c236-f0f6-4fa3-9116-3a22e14a2151", "x": -194.59, "z": -69.2, "ts": "1970-01-21 11:54:51.172000", "event": "Position", "is_bot": false}, {"user_id": "f334c236-f0f6-4fa3-9116-3a22e14a2151", "x": -215.94, "z": -80.99, "ts": "1970-01-21 11:54:51.177000", "event": "Position", "is_bot": false}, {"user_id": "f334c236-f0f6-4fa3-9116-3a22e14a2151", "x": -238.41, "z": -70.37, "ts": "1970-01-21 11:54:51.182000", "event": "Position", "is_bot": false}, {"user_id": "f334c236-f0f6-4fa3-9116-3a22e14a2151", "x": -231.79, "z": -64.92, "ts": "1970-01-21 11:54:51.187000", "event": "Position", "is_bot": false}, {"user_id": "f334c236-f0f6-4fa3-9116-3a22e14a2151", "x": -206.47, "z": -44.18, "ts": "1970-01-21 11:54:51.193000", "event": "Position", "is_bot": false}, {"user_id": "f334c236-f0f6-4fa3-9116-3a22e14a2151", "x": -194.04, "z": -13.94, "ts": "1970-01-21 11:54:51.198000", "event": "Position", "is_bot": false}, {"user_id": "f334c236-f0f6-4fa3-9116-3a22e14a2151", "x": -205.12, "z": 5.37, "ts": "1970-01-21 11:54:51.203000", "event": "Position", "is_bot": false}, {"user_id": "f334c236-f0f6-4fa3-9116-3a22e14a2151", "x": -191.22, "z": 19.65, "ts": "1970-01-21 11:54:51.208000", "event": "Position", "is_bot": false}, {"user_id": "f334c236-f0f6-4fa3-9116-3a22e14a2151", "x": -176.11, "z": 30.41, "ts": "1970-01-21 11:54:51.213000", "event": "Position", "is_bot": false}, {"user_id": "f334c236-f0f6-4fa3-9116-3a22e14a2151", "x": -152.67, "z": 38.21, "ts": "1970-01-21 11:54:51.218000", "event": "Position", "is_bot": false}, {"user_id": "f334c236-f0f6-4fa3-9116-3a22e14a2151", "x": -141.46, "z": 43.64, "ts": "1970-01-21 11:54:51.223000", "event": "Position", "is_bot": false}, {"user_id": "f334c236-f0f6-4fa3-9116-3a22e14a2151", "x": -148.09, "z": 44.72, "ts": "1970-01-21 11:54:51.228000", "event": "Position", "is_bot": false}, {"user_id": "f334c236-f0f6-4fa3-9116-3a22e14a2151", "x": -143.94, "z": 42.92, "ts": "1970-01-21 11:54:51.233000", "event": "Position", "is_bot": false}, {"user_id": "f334c236-f0f6-4fa3-9116-3a22e14a2151", "x": -134.95, "z": 41.62, "ts": "1970-01-21 11:54:51.238000", "event": "Position", "is_bot": false}, {"user_id": "f334c236-f0f6-4fa3-9116-3a22e14a2151", "x": -134.95, "z": 41.62, "ts": "1970-01-21 11:54:51.240000", "event": "Loot", "is_bot": false}, {"user_id": "f334c236-f0f6-4fa3-9116-3a22e14a2151", "x": -132.1, "z": 49.42, "ts": "1970-01-21 11:54:51.243000", "event": "Position", "is_bot": false}, {"user_id": "f334c236-f0f6-4fa3-9116-3a22e14a2151", "x": -127.23, "z": 72.33, "ts": "1970-01-21 11:54:51.248000", "event": "Position", "is_bot": false}, {"user_id": "f334c236-f0f6-4fa3-9116-3a22e14a2151", "x": -126.19, "z": 72.49, "ts": "1970-01-21 11:54:51.248000", "event": "Loot", "is_bot": false}, {"user_id": "f334c236-f0f6-4fa3-9116-3a22e14a2151", "x": -134.68, "z": 81.03, "ts": "1970-01-21 11:54:51.253000", "event": "Position", "is_bot": false}, {"user_id": "f334c236-f0f6-4fa3-9116-3a22e14a2151", "x": -107.77, "z": 88.63, "ts": "1970-01-21 11:54:51.258000", "event": "Position", "is_bot": false}, {"user_id": "f334c236-f0f6-4fa3-9116-3a22e14a2151", "x": -86.6, "z": 101.51, "ts": "1970-01-21 11:54:51.263000", "event": "Position", "is_bot": false}, {"user_id": "f334c236-f0f6-4fa3-9116-3a22e14a2151", "x": -80.03, "z": 122.28, "ts": "1970-01-21 11:54:51.268000", "event": "Position", "is_bot": false}, {"user_id": "f334c236-f0f6-4fa3-9116-3a22e14a2151", "x": -69.44, "z": 138.71, "ts": "1970-01-21 11:54:51.273000", "event": "Position", "is_bot": false}, {"user_id": "f334c236-f0f6-4fa3-9116-3a22e14a2151", "x": -63.93, "z": 160.12, "ts": "1970-01-21 11:54:51.278000", "event": "Position", "is_bot": false}, {"user_id": "f334c236-f0f6-4fa3-9116-3a22e14a2151", "x": -56.9, "z": 172.56, "ts": "1970-01-21 11:54:51.283000", "event": "Position", "is_bot": false}, {"user_id": "f334c236-f0f6-4fa3-9116-3a22e14a2151", "x": -55.72, "z": 173.93, "ts": "1970-01-21 11:54:51.285000", "event": "BotKill", "is_bot": false}, {"user_id": "f334c236-f0f6-4fa3-9116-3a22e14a2151", "x": -51.78, "z": 176.68, "ts": "1970-01-21 11:54:51.288000", "event": "Position", "is_bot": false}, {"user_id": "f334c236-f0f6-4fa3-9116-3a22e14a2151", "x": -30.37, "z": 185.16, "ts": "1970-01-21 11:54:51.293000", "event": "Position", "is_bot": false}, {"user_id": "f334c236-f0f6-4fa3-9116-3a22e14a2151", "x": -13.24, "z": 187.25, "ts": "1970-01-21 11:54:51.297000", "event": "Loot", "is_bot": false}, {"user_id": "f334c236-f0f6-4fa3-9116-3a22e14a2151", "x": -13.24, "z": 187.25, "ts": "1970-01-21 11:54:51.297000", "event": "Loot", "is_bot": false}, {"user_id": "f334c236-f0f6-4fa3-9116-3a22e14a2151", "x": -12.47, "z": 187.82, "ts": "1970-01-21 11:54:51.298000", "event": "Position", "is_bot": false}, {"user_id": "f334c236-f0f6-4fa3-9116-3a22e14a2151", "x": -11.97, "z": 188.62, "ts": "1970-01-21 11:54:51.299000", "event": "Loot", "is_bot": false}, {"user_id": "f334c236-f0f6-4fa3-9116-3a22e14a2151", "x": 2.06, "z": 187.03, "ts": "1970-01-21 11:54:51.303000", "event": "Position", "is_bot": false}, {"user_id": "f334c236-f0f6-4fa3-9116-3a22e14a2151", "x": 6.77, "z": 200.6, "ts": "1970-01-21 11:54:51.307000", "event": "Loot", "is_bot": false}, {"user_id": "f334c236-f0f6-4fa3-9116-3a22e14a2151", "x": 6.42, "z": 202.84, "ts": "1970-01-21 11:54:51.308000", "event": "Position", "is_bot": false}, {"user_id": "f334c236-f0f6-4fa3-9116-3a22e14a2151", "x": 4.61, "z": 230.03, "ts": "1970-01-21 11:54:51.313000", "event": "Position", "is_bot": false}, {"user_id": "f334c236-f0f6-4fa3-9116-3a22e14a2151", "x": -2.35, "z": 229.05, "ts": "1970-01-21 11:54:51.318000", "event": "Position", "is_bot": false}, {"user_id": "f334c236-f0f6-4fa3-9116-3a22e14a2151", "x": 5.18, "z": 228.35, "ts": "1970-01-21 11:54:51.323000", "event": "Position", "is_bot": false}, {"user_id": "f334c236-f0f6-4fa3-9116-3a22e14a2151", "x": 31.87, "z": 234.55, "ts": "1970-01-21 11:54:51.328000", "event": "Position", "is_bot": false}, {"user_id": "f334c236-f0f6-4fa3-9116-3a22e14a2151", "x": 46.6, "z": 239.49, "ts": "1970-01-21 11:54:51.333000", "event": "Position", "is_bot": false}, {"user_id": "f334c236-f0f6-4fa3-9116-3a22e14a2151", "x": 47.24, "z": 240.81, "ts": "1970-01-21 11:54:51.338000", "event": "Position", "is_bot": false}, {"user_id": "f334c236-f0f6-4fa3-9116-3a22e14a2151", "x": 47.0, "z": 239.35, "ts": "1970-01-21 11:54:51.343000", "event": "Position", "is_bot": false}, {"user_id": "f334c236-f0f6-4fa3-9116-3a22e14a2151", "x": 53.7, "z": 241.32, "ts": "1970-01-21 11:54:51.348000", "event": "Position", "is_bot": false}, {"user_id": "f334c236-f0f6-4fa3-9116-3a22e14a2151", "x": 45.66, "z": 242.55, "ts": "1970-01-21 11:54:51.358000", "event": "Position", "is_bot": false}, {"user_id": "f334c236-f0f6-4fa3-9116-3a22e14a2151", "x": 44.8, "z": 244.83, "ts": "1970-01-21 11:54:51.368000", "event": "Position", "is_bot": false}, {"user_id": "f334c236-f0f6-4fa3-9116-3a22e14a2151", "x": 45.97, "z": 243.38, "ts": "1970-01-21 11:54:51.373000", "event": "Position", "is_bot": false}, {"user_id": "f334c236-f0f6-4fa3-9116-3a22e14a2151", "x": 41.58, "z": 250.12, "ts": "1970-01-21 11:54:51.404000", "event": "Position", "is_bot": false}, {"user_id": "f334c236-f0f6-4fa3-9116-3a22e14a2151", "x": 30.82, "z": 251.16, "ts": "1970-01-21 11:54:51.409000", "event": "Position", "is_bot": false}, {"user_id": "f334c236-f0f6-4fa3-9116-3a22e14a2151", "x": 56.9, "z": 247.14, "ts": "1970-01-21 11:54:51.419000", "event": "Position", "is_bot": false}, {"user_id": "f334c236-f0f6-4fa3-9116-3a22e14a2151", "x": 84.97, "z": 232.17, "ts": "1970-01-21 11:54:51.424000", "event": "Position", "is_bot": false}, {"user_id": "f334c236-f0f6-4fa3-9116-3a22e14a2151", "x": 102.54, "z": 227.58, "ts": "1970-01-21 11:54:51.427000", "event": "Loot", "is_bot": false}, {"user_id": "f334c236-f0f6-4fa3-9116-3a22e14a2151", "x": 108.35, "z": 231.7, "ts": "1970-01-21 11:54:51.429000", "event": "Position", "is_bot": false}, {"user_id": "f334c236-f0f6-4fa3-9116-3a22e14a2151", "x": 130.43, "z": 223.77, "ts": "1970-01-21 11:54:51.434000", "event": "Position", "is_bot": false}, {"user_id": "f334c236-f0f6-4fa3-9116-3a22e14a2151", "x": 128.98, "z": 198.26, "ts": "1970-01-21 11:54:51.439000", "event": "Position", "is_bot": false}, {"user_id": "f334c236-f0f6-4fa3-9116-3a22e14a2151", "x": 124.86, "z": 180.55, "ts": "1970-01-21 11:54:51.444000", "event": "Position", "is_bot": false}, {"user_id": "f334c236-f0f6-4fa3-9116-3a22e14a2151", "x": 127.16, "z": 181.78, "ts": "1970-01-21 11:54:51.449000", "event": "Position", "is_bot": false}, {"user_id": "f334c236-f0f6-4fa3-9116-3a22e14a2151", "x": 149.59, "z": 170.96, "ts": "1970-01-21 11:54:51.454000", "event": "Position", "is_bot": false}, {"user_id": "f334c236-f0f6-4fa3-9116-3a22e14a2151", "x": 167.0, "z": 154.97, "ts": "1970-01-21 11:54:51.459000", "event": "Position", "is_bot": false}, {"user_id": "f334c236-f0f6-4fa3-9116-3a22e14a2151", "x": 187.65, "z": 135.16, "ts": "1970-01-21 11:54:51.464000", "event": "Position", "is_bot": false}, {"user_id": "f334c236-f0f6-4fa3-9116-3a22e14a2151", "x": 198.06, "z": 110.42, "ts": "1970-01-21 11:54:51.469000", "event": "Position", "is_bot": false}, {"user_id": "f334c236-f0f6-4fa3-9116-3a22e14a2151", "x": 226.97, "z": 111.99, "ts": "1970-01-21 11:54:51.474000", "event": "Position", "is_bot": false}, {"user_id": "f334c236-f0f6-4fa3-9116-3a22e14a2151", "x": 244.97, "z": 114.07, "ts": "1970-01-21 11:54:51.479000", "event": "Position", "is_bot": false}, {"user_id": "f334c236-f0f6-4fa3-9116-3a22e14a2151", "x": 262.22, "z": 113.97, "ts": "1970-01-21 11:54:51.484000", "event": "Position", "is_bot": false}, {"user_id": "f334c236-f0f6-4fa3-9116-3a22e14a2151", "x": 289.34, "z": 108.96, "ts": "1970-01-21 11:54:51.489000", "event": "Position", "is_bot": false}, {"user_id": "f334c236-f0f6-4fa3-9116-3a22e14a2151", "x": 306.91, "z": 103.39, "ts": "1970-01-21 11:54:51.494000", "event": "Position", "is_bot": false}, {"user_id": "f334c236-f0f6-4fa3-9116-3a22e14a2151", "x": 312.22, "z": 107.85, "ts": "1970-01-21 11:54:51.499000", "event": "Position", "is_bot": false}]}