{"match_id": "a9bd2913-187e-4cb0-afbe-4c0e4a9f2a97", "map_id": "AmbroseValley", "day": "February_11", "events": [{"user_id": "d2f4ec42-e84f-4dca-abdf-6a4154b1c660", "x": -303.56, "z": -346.03, "ts": "1970-01-21 11:52:53.364000", "event": "Position", "is_bot": false}, {"user_id": "d2f4ec42-e84f-4dca-abdf-6a4154b1c660", "x": -295.79, "z": -344.07, "ts": "1970-01-21 11:52:53.380000", "event": "Position", "is_bot": false}, {"user_id": "d2f4ec42-e84f-4dca-abdf-6a4154b1c660", "x": -273.59, "z": -344.79, "ts": "1970-01-21 11:52:53.385000", "event": "Position", "is_bot": false}, {"user_id": "d2f4ec42-e84f-4dca-abdf-6a4154b1c660", "x": -248.34, "z": -335.79, "ts": "1970-01-21 11:52:53.390000", "event": "Position", "is_bot": false}, {"user_id": "d2f4ec42-e84f-4dca-abdf-6a4154b1c660", "x": -227.32, "z": -328.95, "ts": "1970-01-21 11:52:53.395000", "event": "Position", "is_bot": false}, {"user_id": "d2f4ec42-e84f-4dca-abdf-6a4154b1c660", "x": -227.32, "z": -328.95, "ts": "1970-01-21 11:52:53.395000", "event": "Loot", "is_bot": false}, {"user_id": "d2f4ec42-e84f-4dca-abdf-6a4154b1c660", "x": -225.46, "z": -319.55, "ts": "1970-01-21 11:52:53.400000", "event": "Position", "is_bot": false}, {"user_id": "d2f4ec42-e84f-4dca-abdf-6a4154b1c660", "x": -214.43, "z": -325.29, "ts": "1970-01-21 11:52:53.405000", "event": "Position", "is_bot": false}, {"user_id": "d2f4ec42-e84f-4dca-abdf-6a4154b1c660", "x": -216.03, "z": -320.79, "ts": "1970-01-21 11:52:53.410000", "event": "Position", "is_bot": false}, {"user_id": "d2f4ec42-e84f-4dca-abdf-6a4154b1c660", "x": -213.32, "z": -318.08, "ts": "1970-01-21 11:52:53.415000", "event": "Position", "is_bot": false}, {"user_id": "d2f4ec42-e84f-4dca-abdf-6a4154b1c660", "x": -214.13, "z": -318.16, "ts": "1970-01-21 11:52:53.418000", "event": "BotKill", "is_bot": false}, {"user_id": "d2f4ec42-e84f-4dca-abdf-6a4154b1c660", "x": -194.92, "z": -320.63, "ts": "1970-01-21 11:52:53.424000", "event": "Loot", "is_bot": false}, {"user_id": "d2f4ec42-e84f-4dca-abdf-6a4154b1c660", "x": -194.92, "z": -320.63, "ts": "1970-01-21 11:52:53.424000", "event": "Loot", "is_bot": false}, {"user_id": "d2f4ec42-e84f-4dca-abdf-6a4154b1c660", "x": -194.92, "z": -320.63, "ts": "1970-01-21 11:52:53.425000", "event": "Position", "is_bot": false}, {"user_id": "d2f4ec42-e84f-4dca-abdf-6a4154b1c660", "x": -191.68, "z": -318.16, "ts": "1970-01-21 11:52:53.427000", "event": "Loot", "is_bot": false}, {"user_id": "d2f4ec42-e84f-4dca-abdf-6a4154b1c660", "x": -191.64, "z": -319.14, "ts": "1970-01-21 11:52:53.430000", "event": "Position", "is_bot": false}, {"user_id": "d2f4ec42-e84f-4dca-abdf-6a4154b1c660", "x": -191.3, "z": -320.62, "ts": "1970-01-21 11:52:53.435000", "event": "Position", "is_bot": false}, {"user_id": "d2f4ec42-e84f-4dca-abdf-6a4154b1c660", "x": -189.01, "z": -321.46, "ts": "1970-01-21 11:52:53.440000", "event": "Position", "is_bot": false}, {"user_id": "d2f4ec42-e84f-4dca-abdf-6a4154b1c660", "x": -172.33, "z": -310.88, "ts": "1970-01-21 11:52:53.445000", "event": "Position", "is_bot": false}, {"user_id": "d2f4ec42-e84f-4dca-abdf-6a4154b1c660", "x": -151.82, "z": -306.06, "ts": "1970-01-21 11:52:53.450000", "event": "Position", "is_bot": false}, {"user_id": "d2f4ec42-e84f-4dca-abdf-6a4154b1c660", "x": -128.22, "z": -291.42, "ts": "1970-01-21 11:52:53.455000", "event": "Position", "is_bot": false}, {"user_id": "d2f4ec42-e84f-4dca-abdf-6a4154b1c660", "x": -105.27, "z": -280.61, "ts": "1970-01-21 11:52:53.460000", "event": "Position", "is_bot": false}, {"user_id": "d2f4ec42-e84f-4dca-abdf-6a4154b1c660", "x": -99.02, "z": -271.88, "ts": "1970-01-21 11:52:53.465000", "event": "Position", "is_bot": false}, {"user_id": "d2f4ec42-e84f-4dca-abdf-6a4154b1c660", "x": -100.6, "z": -263.11, "ts": "1970-01-21 11:52:53.468000", "event": "Loot", "is_bot": false}, {"user_id": "d2f4ec42-e84f-4dca-abdf-6a4154b1c660", "x": -105.07, "z": -261.37, "ts": "1970-01-21 11:52:53.470000", "event": "Position", "is_bot": false}, {"user_id": "d2f4ec42-e84f-4dca-abdf-6a4154b1c660", "x": -109.86, "z": -259.79, "ts": "1970-01-21 11:52:53.475000", "event": "Position", "is_bot": false}, {"user_id": "d2f4ec42-e84f-4dca-abdf-6a4154b1c660", "x": -121.87, "z": -242.0, "ts": "1970-01-21 11:52:53.480000", "event": "Position", "is_bot": false}, {"user_id": "d2f4ec42-e84f-4dca-abdf-6a4154b1c660", "x": -112.82, "z": -218.38, "ts": "1970-01-21 11:52:53.485000", "event": "Position", "is_bot": false}, {"user_id": "d2f4ec42-e84f-4dca-abdf-6a4154b1c660", "x": -96.92, "z": -193.78, "ts": "1970-01-21 11:52:53.490000", "event": "Position", "is_bot": false}, {"user_id": "d2f4ec42-e84f-4dca-abdf-6a4154b1c660", "x": -82.96, "z": -177.0, "ts": "1970-01-21 11:52:53.495000", "event": "Position", "is_bot": false}, {"user_id": "d2f4ec42-e84f-4dca-abdf-6a4154b1c660", "x": -75.24, "z": -175.04, "ts": "1970-01-21 11:52:53.500000", "event": "Position", "is_bot": false}, {"user_id": "d2f4ec42-e84f-4dca-abdf-6a4154b1c660", "x": -61.5, "z": -192.38, "ts": "1970-01-21 11:52:53.505000", "event": "Position", "is_bot": false}, {"user_id": "d2f4ec42-e84f-4dca-abdf-6a4154b1c660", "x": -69.95, "z": -181.72, "ts": "1970-01-21 11:52:53.510000", "event": "Position", "is_bot": false}, {"user_id": "d2f4ec42-e84f-4dca-abdf-6a4154b1c660", "x": -57.79, "z": -199.54, "ts": "1970-01-21 11:52:53.515000", "event": "Position", "is_bot": false}, {"user_id": "d2f4ec42-e84f-4dca-abdf-6a4154b1c660", "x": -57.94, "z": -199.63, "ts": "1970-01-21 11:52:53.518000", "event": "Loot", "is_bot": false}, {"user_id": "d2f4ec42-e84f-4dca-abdf-6a4154b1c660", "x": -54.88, "z": -196.12, "ts": "1970-01-21 11:52:53.524000", "event": "Loot", "is_bot": false}, {"user_id": "d2f4ec42-e84f-4dca-abdf-6a4154b1c660", "x": -53.63, "z": -195.78, "ts": "1970-01-21 11:52:53.525000", "event": "Position", "is_bot": false}, {"user_id": "d2f4ec42-e84f-4dca-abdf-6a4154b1c660", "x": -51.0, "z": -193.9, "ts": "1970-01-21 11:52:53.530000", "event": "Position", "is_bot": false}, {"user_id": "d2f4ec42-e84f-4dca-abdf-6a4154b1c660", "x": -38.0, "z": -188.18, "ts": "1970-01-21 11:52:53.535000", "event": "Position", "is_bot": false}, {"user_id": "d2f4ec42-e84f-4dca-abdf-6a4154b1c660", "x": -42.28, "z": -188.2, "ts": "1970-01-21 11:52:53.540000", "event": "BotKill", "is_bot": false}, {"user_id": "d2f4ec42-e84f-4dca-abdf-6a4154b1c660", "x": -41.47, "z": -187.89, "ts": "1970-01-21 11:52:53.540000", "event": "Position", "is_bot": false}, {"user_id": "d2f4ec42-e84f-4dca-abdf-6a4154b1c660", "x": -29.73, "z": -182.86, "ts": "1970-01-21 11:52:53.545000", "event": "Loot", "is_bot": false}, {"user_id": "d2f4ec42-e84f-4dca-abdf-6a4154b1c660", "x": -29.73, "z": -182.86, "ts": "1970-01-21 11:52:53.545000", "event": "Position", "is_bot": false}, {"user_id": "d2f4ec42-e84f-4dca-abdf-6a4154b1c660", "x": -13.87, "z": -177.53, "ts": "1970-01-21 11:52:53.550000", "event": "Position", "is_bot": false}, {"user_id": "d2f4ec42-e84f-4dca-abdf-6a4154b1c660", "x": -6.95, "z": -160.95, "ts": "1970-01-21 11:52:53.556000", "event": "Position", "is_bot": false}, {"user_id": "d2f4ec42-e84f-4dca-abdf-6a4154b1c660", "x": -5.12, "z": -140.56, "ts": "1970-01-21 11:52:53.561000", "event": "Position", "is_bot": false}, {"user_id": "d2f4ec42-e84f-4dca-abdf-6a4154b1c660", "x": -2.23, "z": -130.24, "ts": "1970-01-21 11:52:53.566000", "event": "Position", "is_bot": false}, {"user_id": "d2f4ec42-e84f-4dca-abdf-6a4154b1c660", "x": -0.91, "z": -126.48, "ts": "1970-01-21 11:52:53.571000", "event": "Position", "is_bot": false}, {"user_id": "d2f4ec42-e84f-4dca-abdf-6a4154b1c660", "x": -1.77, "z": -117.33, "ts": "1970-01-21 11:52:53.576000", "event": "Position", "is_bot": false}, {"user_id": "d2f4ec42-e84f-4dca-abdf-6a4154b1c660", "x": 3.8, "z": -103.15, "ts": "1970-01-21 11:52:53.581000", "event": "Position", "is_bot": false}, {"user_id": "d2f4ec42-e84f-4dca-abdf-6a4154b1c660", "x": -0.45, "z": -90.37, "ts": "1970-01-21 11:52:53.586000", "event": "Position", "is_bot": false}, {"user_id": "d2f4ec42-e84f-4dca-abdf-6a4154b1c660", "x": -0.45, "z": -90.37, "ts": "1970-01-21 11:52:53.641000", "event": "BotKilled", "is_bot": false}]}